pricegen/__init__.py
pricegen/generator.py
tests/__init__.py
tests/test_generator.py
pricegen-0.0.1.dist-info/LICENSE
pricegen-0.0.1.dist-info/METADATA
pricegen-0.0.1.dist-info/WHEEL
pricegen-0.0.1.dist-info/top_level.txt
pricegen-0.0.1.dist-info/RECORD
