Metadata-Version: 2.1
Name: pricegen
Version: 0.0.1
Summary: Random price generation
Home-page: https://github.com/mahiro/python-pricegen
Author: Mahiro Ando
Author-email: ma514y@gmail.com
License: UNKNOWN
Platform: UNKNOWN
Classifier: Programming Language :: Python :: 3
Classifier: License :: OSI Approved :: MIT License
Classifier: Operating System :: OS Independent
Requires-Python: >=3.6
